bnc_bbt.py
bnc_bbt-1.0.0.dist-info/WHEEL
bnc_bbt-1.0.0.dist-info/METADATA
bnc_bbt-1.0.0.dist-info/RECORD
