Metadata-Version: 2.1
Name: bnc-bbt
Version: 1.0.0
Summary: Bnc
Author: Your Name
Author-email: you@example.com
Requires-Python: >=3.9,<4.0
Classifier: Programming Language :: Python :: 3
Classifier: Programming Language :: Python :: 3.10
Classifier: Programming Language :: Python :: 3.9
